[
  {
    "id": 1,
    "week": "2022-12-03",
    "currentWeek": 40695,
    "baseline": 101387
  },
  {
    "id": 2,
    "week": "2022-12-03",
    "currentWeek": 26989,
    "baseline": 13580
  },
  {
    "id": 3,
    "week": "2022-12-03",
    "currentWeek": 33493,
    "baseline": 99445
  },
  {
    "id": 4,
    "week": "2022-12-03",
    "currentWeek": 30514,
    "baseline": 58386
  },
  {
    "id": 5,
    "week": "2022-12-03",
    "currentWeek": 18431,
    "baseline": 36480
  },
  {
    "id": 6,
    "week": "2022-12-03",
    "currentWeek": 9802,
    "baseline": 14940
  },
  {
    "id": 8,
    "week": "2022-12-03",
    "currentWeek": 42098,
    "baseline": 95028
  },
  {
    "id": 9,
    "week": "2022-12-03",
    "currentWeek": 80071,
    "baseline": 207931
  },
  {
    "id": 10,
    "week": "2022-12-03",
    "currentWeek": 61317,
    "baseline": 138820
  },
  {
    "id": 13,
    "week": "2022-12-03",
    "currentWeek": 26168,
    "baseline": 75749
  },
  {
    "id": 14,
    "week": "2022-12-03",
    "currentWeek": 45544,
    "baseline": 133952
  },
  {
    "id": 16,
    "week": "2022-12-03",
    "currentWeek": 31091,
    "baseline": 102325
  },
  {
    "id": 17,
    "week": "2022-12-03",
    "currentWeek": 26877,
    "baseline": 82127
  },
  {
    "id": 20,
    "week": "2022-12-03",
    "currentWeek": 12605,
    "baseline": 32825
  },
  {
    "id": 22,
    "week": "2022-12-03",
    "currentWeek": 10340,
    "baseline": 38695
  },
  {
    "id": 26,
    "week": "2022-12-03",
    "currentWeek": 53225,
    "baseline": 128702
  },
  {
    "id": 28,
    "week": "2022-12-03",
    "currentWeek": 18481,
    "baseline": 43277
  },
  {
    "id": 30,
    "week": "2022-12-03",
    "currentWeek": 15952,
    "baseline": 34009
  },
  {
    "id": 31,
    "week": "2022-12-03",
    "currentWeek": 11062,
    "baseline": 22173
  },
  {
    "id": 32,
    "week": "2022-12-03",
    "currentWeek": 46852,
    "baseline": 82033
  },
  {
    "id": 33,
    "week": "2022-12-03",
    "currentWeek": 24340,
    "baseline": 46993
  },
  {
    "id": 34,
    "week": "2022-12-03",
    "currentWeek": 29332,
    "baseline": 53391
  },
  {
    "id": 35,
    "week": "2022-12-03",
    "currentWeek": 41497,
    "baseline": 65571
  },
  {
    "id": 36,
    "week": "2022-12-03",
    "currentWeek": 24407,
    "baseline": 45340
  },
  {
    "id": 37,
    "week": "2022-12-03",
    "currentWeek": 15783,
    "baseline": 32408
  },
  {
    "id": 38,
    "week": "2022-12-03",
    "currentWeek": 42799,
    "baseline": 66421
  },
  {
    "id": 39,
    "week": "2022-12-03",
    "currentWeek": 16336,
    "baseline": 34033
  },
  {
    "id": 41,
    "week": "2022-12-03",
    "currentWeek": 21541,
    "baseline": 59177
  },
  {
    "id": 42,
    "week": "2022-12-03",
    "currentWeek": 25546,
    "baseline": 64065
  },
  {
    "id": 43,
    "week": "2022-12-03",
    "currentWeek": 15379,
    "baseline": 37415
  },
  {
    "id": 44,
    "week": "2022-12-03",
    "currentWeek": 43188,
    "baseline": 96689
  },
  {
    "id": 45,
    "week": "2022-12-03",
    "currentWeek": 10051,
    "baseline": 20169
  },
  {
    "id": 46,
    "week": "2022-12-03",
    "currentWeek": 16965,
    "baseline": 37701
  },
  {
    "id": 47,
    "week": "2022-12-03",
    "currentWeek": 29389,
    "baseline": 62860
  },
  {
    "id": 48,
    "week": "2022-12-03",
    "currentWeek": 9539,
    "baseline": 19081
  },
  {
    "id": 49,
    "week": "2022-12-03",
    "currentWeek": 17660,
    "baseline": 34221
  },
  {
    "id": 50,
    "week": "2022-12-03",
    "currentWeek": 18325,
    "baseline": 32750
  },
  {
    "id": 51,
    "week": "2022-12-03",
    "currentWeek": 59682,
    "baseline": 114354
  },
  {
    "id": 52,
    "week": "2022-12-03",
    "currentWeek": 22690,
    "baseline": 44646
  },
  {
    "id": 53,
    "week": "2022-12-03",
    "currentWeek": 13247,
    "baseline": 26618
  },
  {
    "id": 54,
    "week": "2022-12-03",
    "currentWeek": 38104,
    "baseline": 80344
  },
  {
    "id": 55,
    "week": "2022-12-03",
    "currentWeek": 33831,
    "baseline": 72078
  },
  {
    "id": 56,
    "week": "2022-12-03",
    "currentWeek": 10286,
    "baseline": 19949
  },
  {
    "id": 57,
    "week": "2022-12-03",
    "currentWeek": 5688,
    "baseline": 15952
  },
  {
    "id": 58,
    "week": "2022-12-03",
    "currentWeek": 41059,
    "baseline": 88986
  },
  {
    "id": 59,
    "week": "2022-12-03",
    "currentWeek": 19884,
    "baseline": 32839
  },
  {
    "id": 60,
    "week": "2022-12-03",
    "currentWeek": 13671,
    "baseline": 23216
  },
  {
    "id": 61,
    "week": "2022-12-03",
    "currentWeek": 11965,
    "baseline": 18768
  },
  {
    "id": 62,
    "week": "2022-12-03",
    "currentWeek": 6781,
    "baseline": 12354
  },
  {
    "id": 64,
    "week": "2022-12-03",
    "currentWeek": 16949,
    "baseline": 33274
  },
  {
    "id": 65,
    "week": "2022-12-03",
    "currentWeek": 23056,
    "baseline": 37106
  },
  {
    "id": 66,
    "week": "2022-12-03",
    "currentWeek": 20564,
    "baseline": 37440
  },
  {
    "id": 67,
    "week": "2022-12-03",
    "currentWeek": 16371,
    "baseline": 30404
  },
  {
    "id": 68,
    "week": "2022-12-03",
    "currentWeek": 26394,
    "baseline": 47253
  },
  {
    "id": 69,
    "week": "2022-12-03",
    "currentWeek": 15242,
    "baseline": 29320
  },
  {
    "id": 70,
    "week": "2022-12-03",
    "currentWeek": 10653,
    "baseline": 15997
  },
  {
    "id": 71,
    "week": "2022-12-03",
    "currentWeek": 39718,
    "baseline": 72365
  },
  {
    "id": 72,
    "week": "2022-12-03",
    "currentWeek": 23271,
    "baseline": 25982
  },
  {
    "id": 74,
    "week": "2022-12-03",
    "currentWeek": 17688,
    "baseline": 22838
  },
  {
    "id": 75,
    "week": "2022-12-03",
    "currentWeek": 13978,
    "baseline": 21947
  },
  {
    "id": 76,
    "week": "2022-12-03",
    "currentWeek": 23804,
    "baseline": 39901
  },
  {
    "id": 77,
    "week": "2022-12-03",
    "currentWeek": 18333,
    "baseline": 26776
  },
  {
    "id": 78,
    "week": "2022-12-03",
    "currentWeek": 13610,
    "baseline": 19662
  },
  {
    "id": 79,
    "week": "2022-12-03",
    "currentWeek": 9343,
    "baseline": 13802
  },
  {
    "id": 80,
    "week": "2022-12-03",
    "currentWeek": 7719,
    "baseline": 13102
  },
  {
    "id": 81,
    "week": "2022-12-03",
    "currentWeek": 7599,
    "baseline": 6762
  },
  {
    "id": 82,
    "week": "2022-12-03",
    "currentWeek": 8649,
    "baseline": 14995
  },
  {
    "id": 83,
    "week": "2022-12-03",
    "currentWeek": 14490,
    "baseline": 25684
  },
  {
    "id": 84,
    "week": "2022-12-03",
    "currentWeek": 11336,
    "baseline": 20541
  },
  {
    "id": 85,
    "week": "2022-12-03",
    "currentWeek": 10375,
    "baseline": 19808
  },
  {
    "id": 86,
    "week": "2022-12-03",
    "currentWeek": 4455,
    "baseline": 8157
  },
  {
    "id": 87,
    "week": "2022-12-03",
    "currentWeek": 11242,
    "baseline": 26803
  },
  {
    "id": 88,
    "week": "2022-12-03",
    "currentWeek": 7941,
    "baseline": 18231
  },
  {
    "id": 89,
    "week": "2022-12-03",
    "currentWeek": 7614,
    "baseline": 16960
  },
  {
    "id": 90,
    "week": "2022-12-03",
    "currentWeek": 7834,
    "baseline": 15103
  },
  {
    "id": 91,
    "week": "2022-12-03",
    "currentWeek": 6438,
    "baseline": 12444
  },
  {
    "id": 93,
    "week": "2022-12-03",
    "currentWeek": 7451,
    "baseline": 20757
  },
  {
    "id": 94,
    "week": "2022-12-03",
    "currentWeek": 13394,
    "baseline": 40589
  },
  {
    "id": 95,
    "week": "2022-12-03",
    "currentWeek": 15465,
    "baseline": 43343
  },
  {
    "id": 96,
    "week": "2022-12-03",
    "currentWeek": 12192,
    "baseline": 34288
  },
  {
    "id": 97,
    "week": "2022-12-03",
    "currentWeek": 22743,
    "baseline": 73915
  },
  {
    "id": 98,
    "week": "2022-12-03",
    "currentWeek": 20044,
    "baseline": 53254
  },
  {
    "id": 99,
    "week": "2022-12-03",
    "currentWeek": 11213,
    "baseline": 33468
  },
  {
    "id": 100,
    "week": "2022-12-03",
    "currentWeek": 8810,
    "baseline": 21317
  },
  {
    "id": 101,
    "week": "2022-12-03",
    "currentWeek": 22716,
    "baseline": 89514
  },
  {
    "id": 103,
    "week": "2022-12-03",
    "currentWeek": 6559,
    "baseline": 24732
  },
  {
    "id": 107,
    "week": "2022-12-03",
    "currentWeek": 11971,
    "baseline": 42165
  },
  {
    "id": 108,
    "week": "2022-12-03",
    "currentWeek": 12568,
    "baseline": 21179
  },
  {
    "id": 109,
    "week": "2022-12-03",
    "currentWeek": 16306,
    "baseline": 34567
  },
  {
    "id": 110,
    "week": "2022-12-03",
    "currentWeek": 11804,
    "baseline": 25239
  },
  {
    "id": 111,
    "week": "2022-12-03",
    "currentWeek": 7204,
    "baseline": 20690
  },
  {
    "id": 113,
    "week": "2022-12-03",
    "currentWeek": 9642,
    "baseline": 29336
  },
  {
    "id": 114,
    "week": "2022-12-03",
    "currentWeek": 7914,
    "baseline": 27774
  },
  {
    "id": 118,
    "week": "2022-12-03",
    "currentWeek": 14242,
    "baseline": 31880
  },
  {
    "id": 119,
    "week": "2022-12-03",
    "currentWeek": 51677,
    "baseline": 100646
  },
  {
    "id": 120,
    "week": "2022-12-03",
    "currentWeek": 57685,
    "baseline": 148012
  },
  {
    "id": 122,
    "week": "2022-12-03",
    "currentWeek": 19731,
    "baseline": 51395
  },
  {
    "id": 123,
    "week": "2022-12-03",
    "currentWeek": 19038,
    "baseline": 35781
  },
  {
    "id": 124,
    "week": "2022-12-03",
    "currentWeek": 15995,
    "baseline": 36805
  },
  {
    "id": 125,
    "week": "2022-12-03",
    "currentWeek": 14898,
    "baseline": 39813
  },
  {
    "id": 126,
    "week": "2022-12-03",
    "currentWeek": 17067,
    "baseline": 42362
  },
  {
    "id": 127,
    "week": "2022-12-03",
    "currentWeek": 27456,
    "baseline": 61982
  },
  {
    "id": 129,
    "week": "2022-12-03",
    "currentWeek": 21429,
    "baseline": 41529
  },
  {
    "id": 130,
    "week": "2022-12-03",
    "currentWeek": 11539,
    "baseline": 24911
  },
  {
    "id": 131,
    "week": "2022-12-03",
    "currentWeek": 6872,
    "baseline": 11553
  },
  {
    "id": 133,
    "week": "2022-12-03",
    "currentWeek": 5645,
    "baseline": 9433
  },
  {
    "id": 134,
    "week": "2022-12-03",
    "currentWeek": 8366,
    "baseline": 20156
  },
  {
    "id": 135,
    "week": "2022-12-03",
    "currentWeek": 8358,
    "baseline": 16469
  },
  {
    "id": 136,
    "week": "2022-12-03",
    "currentWeek": 12016,
    "baseline": 23692
  },
  {
    "id": 137,
    "week": "2022-12-03",
    "currentWeek": 8512,
    "baseline": 19394
  },
  {
    "id": 138,
    "week": "2022-12-03",
    "currentWeek": 11977,
    "baseline": 64212
  },
  {
    "id": 141,
    "week": "2022-12-03",
    "currentWeek": 4372,
    "baseline": 9940
  },
  {
    "id": 143,
    "week": "2022-12-03",
    "currentWeek": 19628,
    "baseline": 61840
  },
  {
    "id": 144,
    "week": "2022-12-03",
    "currentWeek": 13744,
    "baseline": 42859
  },
  {
    "id": 145,
    "week": "2022-12-03",
    "currentWeek": 9439,
    "baseline": 29027
  },
  {
    "id": 146,
    "week": "2022-12-03",
    "currentWeek": 20666,
    "baseline": 65156
  },
  {
    "id": 147,
    "week": "2022-12-03",
    "currentWeek": 24671,
    "baseline": 80053
  },
  {
    "id": 149,
    "week": "2022-12-03",
    "currentWeek": 10837,
    "baseline": 26592
  },
  {
    "id": 150,
    "week": "2022-12-03",
    "currentWeek": 7413,
    "baseline": 17265
  },
  {
    "id": 151,
    "week": "2022-12-03",
    "currentWeek": 60787,
    "baseline": 141237
  },
  {
    "id": 152,
    "week": "2022-12-03",
    "currentWeek": 14370,
    "baseline": 33587
  },
  {
    "id": 153,
    "week": "2022-12-03",
    "currentWeek": 70721,
    "baseline": 174110
  },
  {
    "id": 154,
    "week": "2022-12-03",
    "currentWeek": 17963,
    "baseline": 43713
  },
  {
    "id": 155,
    "week": "2022-12-03",
    "currentWeek": 17987,
    "baseline": 45720
  },
  {
    "id": 156,
    "week": "2022-12-03",
    "currentWeek": 11744,
    "baseline": 28652
  },
  {
    "id": 157,
    "week": "2022-12-03",
    "currentWeek": 24090,
    "baseline": 58056
  },
  {
    "id": 158,
    "week": "2022-12-03",
    "currentWeek": 26769,
    "baseline": 61333
  },
  {
    "id": 159,
    "week": "2022-12-03",
    "currentWeek": 37609,
    "baseline": 82748
  },
  {
    "id": 160,
    "week": "2022-12-03",
    "currentWeek": 21985,
    "baseline": 54150
  },
  {
    "id": 162,
    "week": "2022-12-03",
    "currentWeek": 53860,
    "baseline": 130723
  },
  {
    "id": 164,
    "week": "2022-12-03",
    "currentWeek": 182426,
    "baseline": 491863
  },
  {
    "id": 165,
    "week": "2022-12-03",
    "currentWeek": 47681,
    "baseline": 137425
  },
  {
    "id": 167,
    "week": "2022-12-03",
    "currentWeek": 84119,
    "baseline": 261263
  },
  {
    "id": 168,
    "week": "2022-12-03",
    "currentWeek": 27393,
    "baseline": 83790
  },
  {
    "id": 169,
    "week": "2022-12-03",
    "currentWeek": 39608,
    "baseline": 121111
  },
  {
    "id": 173,
    "week": "2022-12-03",
    "currentWeek": 23185,
    "baseline": 67306
  },
  {
    "id": 175,
    "week": "2022-12-03",
    "currentWeek": 30366,
    "baseline": 69645
  },
  {
    "id": 176,
    "week": "2022-12-03",
    "currentWeek": 13188,
    "baseline": 29928
  },
  {
    "id": 177,
    "week": "2022-12-03",
    "currentWeek": 15225,
    "baseline": 40932
  },
  {
    "id": 179,
    "week": "2022-12-03",
    "currentWeek": 42241,
    "baseline": 107817
  },
  {
    "id": 180,
    "week": "2022-12-03",
    "currentWeek": 16105,
    "baseline": 39627
  },
  {
    "id": 181,
    "week": "2022-12-03",
    "currentWeek": 36911,
    "baseline": 98687
  },
  {
    "id": 182,
    "week": "2022-12-03",
    "currentWeek": 14306,
    "baseline": 35156
  },
  {
    "id": 183,
    "week": "2022-12-03",
    "currentWeek": 14816,
    "baseline": 34480
  },
  {
    "id": 185,
    "week": "2022-12-03",
    "currentWeek": 8714,
    "baseline": 16227
  },
  {
    "id": 186,
    "week": "2022-12-03",
    "currentWeek": 8449,
    "baseline": 17888
  },
  {
    "id": 187,
    "week": "2022-12-03",
    "currentWeek": 9033,
    "baseline": 18970
  },
  {
    "id": 188,
    "week": "2022-12-03",
    "currentWeek": 28619,
    "baseline": 63616
  },
  {
    "id": 189,
    "week": "2022-12-03",
    "currentWeek": 17052,
    "baseline": 34231
  },
  {
    "id": 190,
    "week": "2022-12-03",
    "currentWeek": 12664,
    "baseline": 25123
  },
  {
    "id": 191,
    "week": "2022-12-03",
    "currentWeek": 8523,
    "baseline": 16572
  },
  {
    "id": 192,
    "week": "2022-12-03",
    "currentWeek": 22796,
    "baseline": 44778
  },
  {
    "id": 193,
    "week": "2022-12-03",
    "currentWeek": 6128,
    "baseline": 10409
  },
  {
    "id": 194,
    "week": "2022-12-03",
    "currentWeek": 7694,
    "baseline": 14752
  },
  {
    "id": 195,
    "week": "2022-12-03",
    "currentWeek": 21979,
    "baseline": 43653
  },
  {
    "id": 196,
    "week": "2022-12-03",
    "currentWeek": 3004,
    "baseline": 11198
  },
  {
    "id": 197,
    "week": "2022-12-03",
    "currentWeek": 2533,
    "baseline": 5176
  },
  {
    "id": 198,
    "week": "2022-12-03",
    "currentWeek": 14137,
    "baseline": 28018
  },
  {
    "id": 199,
    "week": "2022-12-03",
    "currentWeek": 564,
    "baseline": 1837
  },
  {
    "id": 200,
    "week": "2022-12-03",
    "currentWeek": 2006,
    "baseline": 6795
  },
  {
    "id": 201,
    "week": "2022-12-03",
    "currentWeek": 1556,
    "baseline": 3215
  },
  {
    "id": 202,
    "week": "2022-12-03",
    "currentWeek": 673,
    "baseline": 1748
  },
  {
    "id": 203,
    "week": "2022-12-03",
    "currentWeek": 2250,
    "baseline": 4598
  },
  {
    "id": 204,
    "week": "2022-12-03",
    "currentWeek": 6612,
    "baseline": 14012
  },
  {
    "id": 205,
    "week": "2022-12-03",
    "currentWeek": 5910,
    "baseline": 12127
  },
  {
    "id": 206,
    "week": "2022-12-03",
    "currentWeek": 2279,
    "baseline": 4315
  },
  {
    "id": 207,
    "week": "2022-12-03",
    "currentWeek": 3140,
    "baseline": 5727
  },
  {
    "id": 208,
    "week": "2022-12-03",
    "currentWeek": 5543,
    "baseline": 10131
  },
  {
    "id": 209,
    "week": "2022-12-03",
    "currentWeek": 14407,
    "baseline": 26019
  },
  {
    "id": 210,
    "week": "2022-12-03",
    "currentWeek": 19170,
    "baseline": 50907
  },
  {
    "id": 211,
    "week": "2022-12-03",
    "currentWeek": 16790,
    "baseline": 42173
  },
  {
    "id": 212,
    "week": "2022-12-03",
    "currentWeek": 15837,
    "baseline": 47639
  },
  {
    "id": 213,
    "week": "2022-12-03",
    "currentWeek": 28565,
    "baseline": 70682
  },
  {
    "id": 214,
    "week": "2022-12-03",
    "currentWeek": 12562,
    "baseline": 29052
  },
  {
    "id": 215,
    "week": "2022-12-03",
    "currentWeek": 18535,
    "baseline": 58591
  },
  {
    "id": 216,
    "week": "2022-12-03",
    "currentWeek": 11661,
    "baseline": 29165
  },
  {
    "id": 217,
    "week": "2022-12-03",
    "currentWeek": 15728,
    "baseline": 40619
  },
  {
    "id": 218,
    "week": "2022-12-03",
    "currentWeek": 20397,
    "baseline": 53078
  },
  {
    "id": 220,
    "week": "2022-12-03",
    "currentWeek": 9218,
    "baseline": 21712
  },
  {
    "id": 221,
    "week": "2022-12-03",
    "currentWeek": 38668,
    "baseline": 67374
  },
  {
    "id": 222,
    "week": "2022-12-03",
    "currentWeek": 24234,
    "baseline": 45440
  },
  {
    "id": 223,
    "week": "2022-12-03",
    "currentWeek": 55500,
    "baseline": 124851
  },
  {
    "id": 224,
    "week": "2022-12-03",
    "currentWeek": 43041,
    "baseline": 85808
  },
  {
    "id": 225,
    "week": "2022-12-03",
    "currentWeek": 167551,
    "baseline": 351575
  },
  {
    "id": 228,
    "week": "2022-12-03",
    "currentWeek": 62397,
    "baseline": 160182
  },
  {
    "id": 231,
    "week": "2022-12-03",
    "currentWeek": 77209,
    "baseline": 151402
  },
  {
    "id": 232,
    "week": "2022-12-03",
    "currentWeek": 38316,
    "baseline": 104663
  },
  {
    "id": 234,
    "week": "2022-12-03",
    "currentWeek": 37712,
    "baseline": 84618
  },
  {
    "id": 235,
    "week": "2022-12-03",
    "currentWeek": 27375,
    "baseline": 74486
  },
  {
    "id": 236,
    "week": "2022-12-03",
    "currentWeek": 26751,
    "baseline": 67493
  },
  {
    "id": 237,
    "week": "2022-12-03",
    "currentWeek": 27473,
    "baseline": 68533
  },
  {
    "id": 238,
    "week": "2022-12-03",
    "currentWeek": 12203,
    "baseline": 27461
  },
  {
    "id": 240,
    "week": "2022-12-03",
    "currentWeek": 29446,
    "baseline": 70121
  },
  {
    "id": 241,
    "week": "2022-12-03",
    "currentWeek": 15158,
    "baseline": 37549
  },
  {
    "id": 242,
    "week": "2022-12-03",
    "currentWeek": 16272,
    "baseline": 34498
  },
  {
    "id": 243,
    "week": "2022-12-03",
    "currentWeek": 28991,
    "baseline": 59605
  },
  {
    "id": 244,
    "week": "2022-12-03",
    "currentWeek": 12828,
    "baseline": 22418
  },
  {
    "id": 245,
    "week": "2022-12-03",
    "currentWeek": 11413,
    "baseline": 21469
  },
  {
    "id": 246,
    "week": "2022-12-03",
    "currentWeek": 6846,
    "baseline": 11290
  },
  {
    "id": 247,
    "week": "2022-12-03",
    "currentWeek": 4629,
    "baseline": 7067
  },
  {
    "id": 248,
    "week": "2022-12-03",
    "currentWeek": 9178,
    "baseline": 16995
  },
  {
    "id": 249,
    "week": "2022-12-03",
    "currentWeek": 8122,
    "baseline": 14331
  },
  {
    "id": 250,
    "week": "2022-12-03",
    "currentWeek": 11005,
    "baseline": 21708
  },
  {
    "id": 251,
    "week": "2022-12-03",
    "currentWeek": 6424,
    "baseline": 10649
  },
  {
    "id": 252,
    "week": "2022-12-03",
    "currentWeek": 8709,
    "baseline": 15228
  },
  {
    "id": 253,
    "week": "2022-12-03",
    "currentWeek": 5576,
    "baseline": 8357
  },
  {
    "id": 254,
    "week": "2022-12-03",
    "currentWeek": 63087,
    "baseline": 122221
  },
  {
    "id": 255,
    "week": "2022-12-03",
    "currentWeek": 24714,
    "baseline": 47369
  },
  {
    "id": 256,
    "week": "2022-12-03",
    "currentWeek": 23123,
    "baseline": 40623
  },
  {
    "id": 257,
    "week": "2022-12-03",
    "currentWeek": 13349,
    "baseline": 25911
  },
  {
    "id": 258,
    "week": "2022-12-03",
    "currentWeek": 15633,
    "baseline": 29027
  },
  {
    "id": 259,
    "week": "2022-12-03",
    "currentWeek": 69991,
    "baseline": 148103
  },
  {
    "id": 260,
    "week": "2022-12-03",
    "currentWeek": 9110,
    "baseline": 20336
  },
  {
    "id": 261,
    "week": "2022-12-03",
    "currentWeek": 73655,
    "baseline": 155263
  },
  {
    "id": 262,
    "week": "2022-12-03",
    "currentWeek": 23907,
    "baseline": 50824
  },
  {
    "id": 263,
    "week": "2022-12-03",
    "currentWeek": 42727,
    "baseline": 91271
  },
  {
    "id": 264,
    "week": "2022-12-03",
    "currentWeek": 58766,
    "baseline": 121988
  },
  {
    "id": 265,
    "week": "2022-12-03",
    "currentWeek": 54620,
    "baseline": 109817
  },
  {
    "id": 266,
    "week": "2022-12-03",
    "currentWeek": 38231,
    "baseline": 74120
  },
  {
    "id": 268,
    "week": "2022-12-03",
    "currentWeek": 10424,
    "baseline": 21066
  },
  {
    "id": 269,
    "week": "2022-12-03",
    "currentWeek": 19272,
    "baseline": 38913
  },
  {
    "id": 270,
    "week": "2022-12-03",
    "currentWeek": 21597,
    "baseline": 49893
  },
  {
    "id": 271,
    "week": "2022-12-03",
    "currentWeek": 32683,
    "baseline": 89409
  },
  {
    "id": 272,
    "week": "2022-12-03",
    "currentWeek": 10706,
    "baseline": 27004
  },
  {
    "id": 273,
    "week": "2022-12-03",
    "currentWeek": 32310,
    "baseline": 83938
  },
  {
    "id": 276,
    "week": "2022-12-03",
    "currentWeek": 45882,
    "baseline": 146756
  },
  {
    "id": 277,
    "week": "2022-12-03",
    "currentWeek": 38000,
    "baseline": 104530
  },
  {
    "id": 278,
    "week": "2022-12-03",
    "currentWeek": 93195,
    "baseline": 195143
  },
  {
    "id": 279,
    "week": "2022-12-03",
    "currentWeek": 136920,
    "baseline": 220057
  },
  {
    "id": 280,
    "week": "2022-12-03",
    "currentWeek": 13768,
    "baseline": 27067
  },
  {
    "id": 282,
    "week": "2022-12-03",
    "currentWeek": 4566,
    "baseline": 10165
  },
  {
    "id": 283,
    "week": "2022-12-03",
    "currentWeek": 23777,
    "baseline": 58671
  },
  {
    "id": 284,
    "week": "2022-12-03",
    "currentWeek": 21387,
    "baseline": 59402
  },
  {
    "id": 286,
    "week": "2022-12-03",
    "currentWeek": 14236,
    "baseline": 28923
  },
  {
    "id": 287,
    "week": "2022-12-03",
    "currentWeek": 10157,
    "baseline": 14019
  },
  {
    "id": 288,
    "week": "2022-12-03",
    "currentWeek": 14394,
    "baseline": 34932
  },
  {
    "id": 289,
    "week": "2022-12-03",
    "currentWeek": 18685,
    "baseline": 53523
  },
  {
    "id": 290,
    "week": "2022-12-03",
    "currentWeek": 13154,
    "baseline": 33024
  },
  {
    "id": 291,
    "week": "2022-12-03",
    "currentWeek": 12146,
    "baseline": 30810
  },
  {
    "id": 292,
    "week": "2022-12-03",
    "currentWeek": 18467,
    "baseline": 33623
  },
  {
    "id": 293,
    "week": "2022-12-03",
    "currentWeek": 23074,
    "baseline": 42737
  },
  {
    "id": 294,
    "week": "2022-12-03",
    "currentWeek": 12798,
    "baseline": 23471
  },
  {
    "id": 295,
    "week": "2022-12-03",
    "currentWeek": 28233,
    "baseline": 55814
  },
  {
    "id": 296,
    "week": "2022-12-03",
    "currentWeek": 16410,
    "baseline": 30014
  },
  {
    "id": 297,
    "week": "2022-12-03",
    "currentWeek": 7306,
    "baseline": 10586
  },
  {
    "id": 298,
    "week": "2022-12-03",
    "currentWeek": 22991,
    "baseline": 35848
  },
  {
    "id": 299,
    "week": "2022-12-03",
    "currentWeek": 25053,
    "baseline": 39717
  },
  {
    "id": 300,
    "week": "2022-12-03",
    "currentWeek": 25230,
    "baseline": 44151
  },
  {
    "id": 301,
    "week": "2022-12-03",
    "currentWeek": 35872,
    "baseline": 67359
  },
  {
    "id": 303,
    "week": "2022-12-03",
    "currentWeek": 32819,
    "baseline": 71504
  },
  {
    "id": 304,
    "week": "2022-12-03",
    "currentWeek": 28647,
    "baseline": 56117
  },
  {
    "id": 305,
    "week": "2022-12-03",
    "currentWeek": 37349,
    "baseline": 74451
  },
  {
    "id": 306,
    "week": "2022-12-03",
    "currentWeek": 21770,
    "baseline": 45076
  },
  {
    "id": 307,
    "week": "2022-12-03",
    "currentWeek": 28739,
    "baseline": 82923
  },
  {
    "id": 308,
    "week": "2022-12-03",
    "currentWeek": 31025,
    "baseline": 69870
  },
  {
    "id": 309,
    "week": "2022-12-03",
    "currentWeek": 34665,
    "baseline": 71357
  },
  {
    "id": 310,
    "week": "2022-12-03",
    "currentWeek": 94663,
    "baseline": 221113
  },
  {
    "id": 311,
    "week": "2022-12-03",
    "currentWeek": 48526,
    "baseline": 107044
  },
  {
    "id": 312,
    "week": "2022-12-03",
    "currentWeek": 40831,
    "baseline": 89953
  },
  {
    "id": 313,
    "week": "2022-12-03",
    "currentWeek": 98483,
    "baseline": 233353
  },
  {
    "id": 314,
    "week": "2022-12-03",
    "currentWeek": 58443,
    "baseline": 132213
  },
  {
    "id": 316,
    "week": "2022-12-03",
    "currentWeek": 71884,
    "baseline": 152973
  },
  {
    "id": 318,
    "week": "2022-12-03",
    "currentWeek": 190163,
    "baseline": 498547
  },
  {
    "id": 319,
    "week": "2022-12-03",
    "currentWeek": 33046,
    "baseline": 85041
  },
  {
    "id": 320,
    "week": "2022-12-03",
    "currentWeek": 33784,
    "baseline": 87188
  },
  {
    "id": 321,
    "week": "2022-12-03",
    "currentWeek": 18987,
    "baseline": 49713
  },
  {
    "id": 323,
    "week": "2022-12-03",
    "currentWeek": 26185,
    "baseline": 63598
  },
  {
    "id": 324,
    "week": "2022-12-03",
    "currentWeek": 26672,
    "baseline": 84960
  },
  {
    "id": 325,
    "week": "2022-12-03",
    "currentWeek": 11913,
    "baseline": 37777
  },
  {
    "id": 326,
    "week": "2022-12-03",
    "currentWeek": 13654,
    "baseline": 29920
  },
  {
    "id": 327,
    "week": "2022-12-03",
    "currentWeek": 49225,
    "baseline": 112734
  },
  {
    "id": 328,
    "week": "2022-12-03",
    "currentWeek": 36068,
    "baseline": 82860
  },
  {
    "id": 329,
    "week": "2022-12-03",
    "currentWeek": 18652,
    "baseline": 50149
  },
  {
    "id": 333,
    "week": "2022-12-03",
    "currentWeek": 40068,
    "baseline": 132942
  },
  {
    "id": 334,
    "week": "2022-12-03",
    "currentWeek": 15118,
    "baseline": 34161
  },
  {
    "id": 336,
    "week": "2022-12-03",
    "currentWeek": 21076,
    "baseline": 44168
  },
  {
    "id": 337,
    "week": "2022-12-03",
    "currentWeek": 24807,
    "baseline": 60220
  },
  {
    "id": 339,
    "week": "2022-12-03",
    "currentWeek": 9865,
    "baseline": 23168
  },
  {
    "id": 340,
    "week": "2022-12-03",
    "currentWeek": 18592,
    "baseline": 43832
  },
  {
    "id": 341,
    "week": "2022-12-03",
    "currentWeek": 11387,
    "baseline": 25718
  },
  {
    "id": 343,
    "week": "2022-12-03",
    "currentWeek": 10610,
    "baseline": 26216
  },
  {
    "id": 344,
    "week": "2022-12-03",
    "currentWeek": 12874,
    "baseline": 28356
  },
  {
    "id": 345,
    "week": "2022-12-03",
    "currentWeek": 77325,
    "baseline": 153860
  },
  {
    "id": 346,
    "week": "2022-12-03",
    "currentWeek": 18140,
    "baseline": 37891
  },
  {
    "id": 347,
    "week": "2022-12-03",
    "currentWeek": 13535,
    "baseline": 30297
  },
  {
    "id": 348,
    "week": "2022-12-03",
    "currentWeek": 12606,
    "baseline": 28218
  },
  {
    "id": 349,
    "week": "2022-12-03",
    "currentWeek": 6803,
    "baseline": 13154
  },
  {
    "id": 350,
    "week": "2022-12-03",
    "currentWeek": 11825,
    "baseline": 26421
  },
  {
    "id": 351,
    "week": "2022-12-03",
    "currentWeek": 6863,
    "baseline": 16530
  },
  {
    "id": 352,
    "week": "2022-12-03",
    "currentWeek": 14735,
    "baseline": 32894
  },
  {
    "id": 353,
    "week": "2022-12-03",
    "currentWeek": 10344,
    "baseline": 20115
  },
  {
    "id": 354,
    "week": "2022-12-03",
    "currentWeek": 16193,
    "baseline": 31908
  },
  {
    "id": 355,
    "week": "2022-12-03",
    "currentWeek": 21208,
    "baseline": 36402
  },
  {
    "id": 356,
    "week": "2022-12-03",
    "currentWeek": 28543,
    "baseline": 55469
  },
  {
    "id": 357,
    "week": "2022-12-03",
    "currentWeek": 13691,
    "baseline": 24903
  },
  {
    "id": 358,
    "week": "2022-12-03",
    "currentWeek": 22187,
    "baseline": 41491
  },
  {
    "id": 359,
    "week": "2022-12-03",
    "currentWeek": 55994,
    "baseline": 111871
  },
  {
    "id": 360,
    "week": "2022-12-03",
    "currentWeek": 18723,
    "baseline": 42226
  },
  {
    "id": 361,
    "week": "2022-12-03",
    "currentWeek": 11203,
    "baseline": 22121
  },
  {
    "id": 362,
    "week": "2022-12-03",
    "currentWeek": 6123,
    "baseline": 11724
  },
  {
    "id": 363,
    "week": "2022-12-03",
    "currentWeek": 16800,
    "baseline": 34799
  },
  {
    "id": 364,
    "week": "2022-12-03",
    "currentWeek": 7458,
    "baseline": 15338
  },
  {
    "id": 365,
    "week": "2022-12-03",
    "currentWeek": 18793,
    "baseline": 37706
  },
  {
    "id": 366,
    "week": "2022-12-03",
    "currentWeek": 44161,
    "baseline": 91518
  },
  {
    "id": 367,
    "week": "2022-12-03",
    "currentWeek": 13310,
    "baseline": 24515
  },
  {
    "id": 368,
    "week": "2022-12-03",
    "currentWeek": 19714,
    "baseline": 37783
  },
  {
    "id": 369,
    "week": "2022-12-03",
    "currentWeek": 20926,
    "baseline": 38226
  },
  {
    "id": 370,
    "week": "2022-12-03",
    "currentWeek": 6071,
    "baseline": 11235
  },
  {
    "id": 371,
    "week": "2022-12-03",
    "currentWeek": 31381,
    "baseline": 61136
  },
  {
    "id": 372,
    "week": "2022-12-03",
    "currentWeek": 11332,
    "baseline": 18325
  },
  {
    "id": 373,
    "week": "2022-12-03",
    "currentWeek": 14784,
    "baseline": 28273
  },
  {
    "id": 374,
    "week": "2022-12-03",
    "currentWeek": 4601,
    "baseline": 6089
  },
  {
    "id": 375,
    "week": "2022-12-03",
    "currentWeek": 8247,
    "baseline": 20151
  },
  {
    "id": 376,
    "week": "2022-12-03",
    "currentWeek": 18380,
    "baseline": 35065
  },
  {
    "id": 377,
    "week": "2022-12-03",
    "currentWeek": 22610,
    "baseline": 48264
  },
  {
    "id": 378,
    "week": "2022-12-03",
    "currentWeek": 20241,
    "baseline": 40591
  },
  {
    "id": 379,
    "week": "2022-12-03",
    "currentWeek": 27337,
    "baseline": 47828
  },
  {
    "id": 380,
    "week": "2022-12-03",
    "currentWeek": 20473,
    "baseline": 29752
  },
  {
    "id": 381,
    "week": "2022-12-03",
    "currentWeek": 29866,
    "baseline": 52048
  },
  {
    "id": 382,
    "week": "2022-12-03",
    "currentWeek": 34465,
    "baseline": 59677
  },
  {
    "id": 383,
    "week": "2022-12-03",
    "currentWeek": 20319,
    "baseline": 34008
  },
  {
    "id": 384,
    "week": "2022-12-03",
    "currentWeek": 31675,
    "baseline": 59753
  },
  {
    "id": 385,
    "week": "2022-12-03",
    "currentWeek": 17914,
    "baseline": 32805
  },
  {
    "id": 386,
    "week": "2022-12-03",
    "currentWeek": 16699,
    "baseline": 29413
  },
  {
    "id": 387,
    "week": "2022-12-03",
    "currentWeek": 25661,
    "baseline": 47534
  },
  {
    "id": 388,
    "week": "2022-12-03",
    "currentWeek": 31303,
    "baseline": 50478
  },
  {
    "id": 391,
    "week": "2022-12-03",
    "currentWeek": 11802,
    "baseline": 19925
  },
  {
    "id": 392,
    "week": "2022-12-03",
    "currentWeek": 65235,
    "baseline": 164398
  },
  {
    "id": 393,
    "week": "2022-12-03",
    "currentWeek": 43856,
    "baseline": 87400
  },
  {
    "id": 394,
    "week": "2022-12-03",
    "currentWeek": 30382,
    "baseline": 62897
  },
  {
    "id": 395,
    "week": "2022-12-03",
    "currentWeek": 35837,
    "baseline": 76992
  },
  {
    "id": 396,
    "week": "2022-12-03",
    "currentWeek": 45228,
    "baseline": 98236
  },
  {
    "id": 397,
    "week": "2022-12-03",
    "currentWeek": 116191,
    "baseline": 256051
  },
  {
    "id": 398,
    "week": "2022-12-03",
    "currentWeek": 68839,
    "baseline": 147389
  },
  {
    "id": 399,
    "week": "2022-12-03",
    "currentWeek": 60561,
    "baseline": 127643
  },
  {
    "id": 403,
    "week": "2022-12-03",
    "currentWeek": 56514,
    "baseline": 165225
  },
  {
    "id": 404,
    "week": "2022-12-03",
    "currentWeek": 43867,
    "baseline": 108663
  },
  {
    "id": 405,
    "week": "2022-12-03",
    "currentWeek": 62017,
    "baseline": 160560
  },
  {
    "id": 407,
    "week": "2022-12-03",
    "currentWeek": 32274,
    "baseline": 99882
  },
  {
    "id": 409,
    "week": "2022-12-03",
    "currentWeek": 26277,
    "baseline": 68774
  },
  {
    "id": 413,
    "week": "2022-12-03",
    "currentWeek": 34060,
    "baseline": 106312
  },
  {
    "id": 414,
    "week": "2022-12-03",
    "currentWeek": 68409,
    "baseline": 166103
  },
  {
    "id": 416,
    "week": "2022-12-03",
    "currentWeek": 15092,
    "baseline": 28037
  },
  {
    "id": 417,
    "week": "2022-12-03",
    "currentWeek": 10248,
    "baseline": 19319
  },
  {
    "id": 418,
    "week": "2022-12-03",
    "currentWeek": 14276,
    "baseline": 27664
  },
  {
    "id": 419,
    "week": "2022-12-03",
    "currentWeek": 10520,
    "baseline": 22909
  },
  {
    "id": 420,
    "week": "2022-12-03",
    "currentWeek": 8402,
    "baseline": 18743
  },
  {
    "id": 421,
    "week": "2022-12-03",
    "currentWeek": 18830,
    "baseline": 43617
  },
  {
    "id": 422,
    "week": "2022-12-03",
    "currentWeek": 8552,
    "baseline": 19265
  },
  {
    "id": 423,
    "week": "2022-12-03",
    "currentWeek": 14472,
    "baseline": 30968
  },
  {
    "id": 424,
    "week": "2022-12-03",
    "currentWeek": 21881,
    "baseline": 50847
  },
  {
    "id": 425,
    "week": "2022-12-03",
    "currentWeek": 7127,
    "baseline": 14764
  },
  {
    "id": 426,
    "week": "2022-12-03",
    "currentWeek": 24578,
    "baseline": 43460
  },
  {
    "id": 427,
    "week": "2022-12-03",
    "currentWeek": 15729,
    "baseline": 40581
  },
  {
    "id": 428,
    "week": "2022-12-03",
    "currentWeek": 18425,
    "baseline": 39508
  },
  {
    "id": 429,
    "week": "2022-12-03",
    "currentWeek": 13100,
    "baseline": 26182
  },
  {
    "id": 430,
    "week": "2022-12-03",
    "currentWeek": 22254,
    "baseline": 50050
  },
  {
    "id": 431,
    "week": "2022-12-03",
    "currentWeek": 9910,
    "baseline": 18618
  },
  {
    "id": 432,
    "week": "2022-12-03",
    "currentWeek": 20316,
    "baseline": 41245
  },
  {
    "id": 433,
    "week": "2022-12-03",
    "currentWeek": 15353,
    "baseline": 30378
  },
  {
    "id": 434,
    "week": "2022-12-03",
    "currentWeek": 54192,
    "baseline": 129843
  },
  {
    "id": 436,
    "week": "2022-12-03",
    "currentWeek": 9974,
    "baseline": 21889
  },
  {
    "id": 437,
    "week": "2022-12-03",
    "currentWeek": 9364,
    "baseline": 18860
  },
  {
    "id": 438,
    "week": "2022-12-03",
    "currentWeek": 32805,
    "baseline": 80305
  },
  {
    "id": 439,
    "week": "2022-12-03",
    "currentWeek": 36531,
    "baseline": 88217
  },
  {
    "id": 440,
    "week": "2022-12-03",
    "currentWeek": 28317,
    "baseline": 63651
  },
  {
    "id": 441,
    "week": "2022-12-03",
    "currentWeek": 20074,
    "baseline": 50833
  },
  {
    "id": 442,
    "week": "2022-12-03",
    "currentWeek": 12534,
    "baseline": 25863
  },
  {
    "id": 443,
    "week": "2022-12-03",
    "currentWeek": 8782,
    "baseline": 21290
  },
  {
    "id": 444,
    "week": "2022-12-03",
    "currentWeek": 13749,
    "baseline": 24155
  },
  {
    "id": 445,
    "week": "2022-12-03",
    "currentWeek": 8536,
    "baseline": 17410
  },
  {
    "id": 446,
    "week": "2022-12-03",
    "currentWeek": 6891,
    "baseline": 13724
  },
  {
    "id": 447,
    "week": "2022-12-03",
    "currentWeek": 189620,
    "baseline": 337657
  },
  {
    "id": 448,
    "week": "2022-12-03",
    "currentWeek": 8153,
    "baseline": 38461
  },
  {
    "id": 449,
    "week": "2022-12-03",
    "currentWeek": 43502,
    "baseline": 72982
  },
  {
    "id": 450,
    "week": "2022-12-03",
    "currentWeek": 88160,
    "baseline": 122330
  },
  {
    "id": 451,
    "week": "2022-12-03",
    "currentWeek": 92111,
    "baseline": 131383
  },
  {
    "id": 452,
    "week": "2022-12-03",
    "currentWeek": 61743,
    "baseline": 100850
  },
  {
    "id": 453,
    "week": "2022-12-03",
    "currentWeek": 60147,
    "baseline": 93474
  },
  {
    "id": 455,
    "week": "2022-12-03",
    "currentWeek": 20537,
    "baseline": 29859
  },
  {
    "id": 456,
    "week": "2022-12-03",
    "currentWeek": 58817,
    "baseline": 102194
  },
  {
    "id": 457,
    "week": "2022-12-03",
    "currentWeek": 18601,
    "baseline": 35948
  },
  {
    "id": 458,
    "week": "2022-12-03",
    "currentWeek": 38222,
    "baseline": 76546
  },
  {
    "id": 459,
    "week": "2022-12-03",
    "currentWeek": 28621,
    "baseline": 58638
  },
  {
    "id": 460,
    "week": "2022-12-03",
    "currentWeek": 26976,
    "baseline": 55258
  },
  {
    "id": 461,
    "week": "2022-12-03",
    "currentWeek": 38581,
    "baseline": 96260
  },
  {
    "id": 463,
    "week": "2022-12-03",
    "currentWeek": 15576,
    "baseline": 36408
  },
  {
    "id": 464,
    "week": "2022-12-03",
    "currentWeek": 34691,
    "baseline": 88452
  },
  {
    "id": 471,
    "week": "2022-12-03",
    "currentWeek": 57549,
    "baseline": 116642
  },
  {
    "id": 475,
    "week": "2022-12-03",
    "currentWeek": 43967,
    "baseline": 117728
  },
  {
    "id": 476,
    "week": "2022-12-03",
    "currentWeek": 49458,
    "baseline": 158520
  },
  {
    "id": 477,
    "week": "2022-12-03",
    "currentWeek": 65053,
    "baseline": 180288
  },
  {
    "id": 601,
    "week": "2022-12-03",
    "currentWeek": 101775,
    "baseline": 277293
  },
  {
    "id": 602,
    "week": "2022-12-03",
    "currentWeek": 215882,
    "baseline": 599943
  },
  {
    "id": 603,
    "week": "2022-12-03",
    "currentWeek": 32271,
    "baseline": 75200
  },
  {
    "id": 604,
    "week": "2022-12-03",
    "currentWeek": 62513,
    "baseline": 154115
  },
  {
    "id": 605,
    "week": "2022-12-03",
    "currentWeek": 69523,
    "baseline": 117178
  },
  {
    "id": 606,
    "week": "2022-12-03",
    "currentWeek": 53744,
    "baseline": 134448
  },
  {
    "id": 607,
    "week": "2022-12-03",
    "currentWeek": 274860,
    "baseline": 744704
  },
  {
    "id": 608,
    "week": "2022-12-03",
    "currentWeek": 33114,
    "baseline": 74907
  },
  {
    "id": 609,
    "week": "2022-12-03",
    "currentWeek": 129105,
    "baseline": 320771
  },
  {
    "id": 610,
    "week": "2022-12-03",
    "currentWeek": 301588,
    "baseline": 854307
  },
  {
    "id": 611,
    "week": "2022-12-03",
    "currentWeek": 472296,
    "baseline": 1227289
  },
  {
    "id": 612,
    "week": "2022-12-03",
    "currentWeek": 119605,
    "baseline": 358935
  },
  {
    "id": 613,
    "week": "2022-12-03",
    "currentWeek": 133052,
    "baseline": 315848
  },
  {
    "id": 614,
    "week": "2022-12-03",
    "currentWeek": 181766,
    "baseline": 436373
  },
  {
    "id": 615,
    "week": "2022-12-03",
    "currentWeek": 18266,
    "baseline": 28615
  },
  {
    "id": 616,
    "week": "2022-12-03",
    "currentWeek": 172429,
    "baseline": 323492
  },
  {
    "id": 617,
    "week": "2022-12-03",
    "currentWeek": 126260,
    "baseline": 263130
  },
  {
    "id": 618,
    "week": "2022-12-03",
    "currentWeek": 97920,
    "baseline": 267998
  },
  {
    "id": 619,
    "week": "2022-12-03",
    "currentWeek": 77159,
    "baseline": 228338
  },
  {
    "id": 620,
    "week": "2022-12-03",
    "currentWeek": 78066,
    "baseline": 195343
  },
  {
    "id": 621,
    "week": "2022-12-03",
    "currentWeek": 23792,
    "baseline": 55326
  },
  {
    "id": 622,
    "week": "2022-12-03",
    "currentWeek": 75905,
    "baseline": 171665
  },
  {
    "id": 623,
    "week": "2022-12-03",
    "currentWeek": 108572,
    "baseline": 295178
  },
  {
    "id": 624,
    "week": "2022-12-03",
    "currentWeek": 140676,
    "baseline": 398544
  },
  {
    "id": 625,
    "week": "2022-12-03",
    "currentWeek": 65499,
    "baseline": 166436
  },
  {
    "id": 626,
    "week": "2022-12-03",
    "currentWeek": 37026,
    "baseline": 96289
  },
  {
    "id": 627,
    "week": "2022-12-03",
    "currentWeek": 13456,
    "baseline": 38041
  },
  {
    "id": 628,
    "week": "2022-12-03",
    "currentWeek": 195035,
    "baseline": 518410
  },
  {
    "id": 629,
    "week": "2022-12-03",
    "currentWeek": 29673,
    "baseline": 88898
  },
  {
    "id": 630,
    "week": "2022-12-03",
    "currentWeek": 60125,
    "baseline": 113730
  },
  {
    "id": 635,
    "week": "2022-12-03",
    "currentWeek": 71242,
    "baseline": 199633
  },
  {
    "id": 636,
    "week": "2022-12-03",
    "currentWeek": 94900,
    "baseline": 238422
  }
]